README.rst
setup.py
pgtool/__init__.py
pgtool/pgtool.py
pgtool.egg-info/PKG-INFO
pgtool.egg-info/SOURCES.txt
pgtool.egg-info/dependency_links.txt
pgtool.egg-info/entry_points.txt
pgtool.egg-info/requires.txt
pgtool.egg-info/top_level.txt