Metadata-Version: 1.1
Name: pgtool
Version: 0.0.1
Summary: Command-line tool to simplify some common maintenance tasks on PostgreSQL databases
Home-page: https://github.com/voicecom/pgtool
Author: Marti Raudsepp
Author-email: marti@voicecom.ee
License: Apache Software License
Download-URL: https://pypi.python.org/pypi/pgtool/
Keywords: postgresql tool maintenance admin reindex concurrently rename move copy duplicate databases voicecom
Platform: any
Classifier: Development Status :: 4 - Beta
Classifier: Environment :: Console
Classifier: Intended Audience :: Developers
Classifier: Intended Audience :: System Administrators
Classifier: License :: OSI Approved :: Apache Software License
Classifier: Programming Language :: Python :: 2.7
Classifier: Programming Language :: Python :: 3.4
Classifier: Programming Language :: Python :: 3.5
Classifier: Topic :: Database :: Front-Ends
Classifier: Topic :: System :: Systems Administration
